pikernel/__init__.py
pikernel/dimension_1.py
pikernel/dimension_2.py
pikernel/kernel.py
pikernel/utils.py
pikernel-1.0.2.dist-info/METADATA
pikernel-1.0.2.dist-info/WHEEL
pikernel-1.0.2.dist-info/licenses/LICENSE
pikernel-1.0.2.dist-info/RECORD
