Metadata-Version: 2.4
Name: pikernel
Version: 1.0.2
Summary: A package implementing physics-informed kernels in dimensions 1 and 2
Project-URL: Homepage, https://github.com/NathanDoumeche/pikernel
Project-URL: Issues, https://github.com/NathanDoumeche/pikernel/issues
Author-email: Nathan Doumèche <nathan.doumeche@gmail.com>, Francis Bach <francis.bach@inria.fr>, Claire Boyer <claire.boyer@universite-paris-saclay.fr>, Gérard Biau <gerard.biau@sorbonne-universite.fr>
License-Expression: MIT
License-File: LICENSE
Classifier: Operating System :: OS Independent
Classifier: Programming Language :: Python :: 3
Requires-Python: >=3.9
Requires-Dist: matplotlib>=3.9.0
Requires-Dist: numpy>=2.0.0
Requires-Dist: pandas>=2.2.2
Requires-Dist: torch>=2.6.0
